antiblock_scrapy_selenium/__init__.py
antiblock_scrapy_selenium/http.py
antiblock_scrapy_selenium/middlewares.py
antiblock_scrapy_selenium-0.0.1.dist-info/LICENSE
antiblock_scrapy_selenium-0.0.1.dist-info/METADATA
antiblock_scrapy_selenium-0.0.1.dist-info/WHEEL
antiblock_scrapy_selenium-0.0.1.dist-info/top_level.txt
antiblock_scrapy_selenium-0.0.1.dist-info/RECORD
