Metadata-Version: 2.1
Name: antiblock-scrapy-selenium
Version: 0.0.1
Summary: Mecanismos antibloqueios para Scrapy-Selenium
Home-page: https://github.com/elvesrodrigues/antiblock-scrapy-selenium
Author: Elves M. Rodrigues
Author-email: elvesmateusrodrigues@gmail.com
License: UNKNOWN
Platform: UNKNOWN
Classifier: Programming Language :: Python :: 3
Classifier: License :: OSI Approved :: MIT License
Classifier: Operating System :: Unix
Requires-Python: >=3.0
Requires-Dist: selenium
Requires-Dist: antiblock-selenium
